chemreader/__init__.py
chemreader/readers/__init__.py
chemreader/readers/basereader.py
chemreader/readers/canonical_atom_order.py
chemreader/readers/readmol.py
chemreader/readers/readmol2.py
chemreader/readers/readpdb.py
chemreader/readers/readsmiles.py
chemreader/tests/__init__.py
chemreader/tests/test_graph_writer.py
chemreader/tests/test_read.py
chemreader/utils/__init__.py
chemreader/utils/tools.py
chemreader/writers/__init__.py
chemreader/writers/graph_writers.py
chemreader-0.3.11.dist-info/LICENSE
chemreader-0.3.11.dist-info/METADATA
chemreader-0.3.11.dist-info/WHEEL
chemreader-0.3.11.dist-info/top_level.txt
chemreader-0.3.11.dist-info/RECORD
