Metadata-Version: 2.1
Name: chemreader
Version: 0.3.11
Summary: Read data from typical chemical file formats
Home-page: https://github.com/thomasly/chem_reader
Author: Yang Liu
Author-email: thomasliuy@gmail.com
License: UNKNOWN
Download-URL: https://github.com/thomasly/chem_reader/archive/v0.3.11.tar.gz
Platform: UNKNOWN
Classifier: Programming Language :: Python :: 3.6
Classifier: License :: OSI Approved :: MIT License
Classifier: Operating System :: OS Independent
Requires-Python: >=3.6
Requires-Dist: numpy
Requires-Dist: scipy
